.gitignore
MANIFEST.in
README.md
setup.py
cache_toolbox/__init__.py
cache_toolbox/app_settings.py
cache_toolbox/core.py
cache_toolbox/middleware.py
cache_toolbox/model.py
cache_toolbox/relation.py
cache_toolbox/templatetags/__init__.py
cache_toolbox/templatetags/cache_toolbox.py
django_cache_toolbox_modified.egg-info/PKG-INFO
django_cache_toolbox_modified.egg-info/SOURCES.txt
django_cache_toolbox_modified.egg-info/dependency_links.txt
django_cache_toolbox_modified.egg-info/not-zip-safe
django_cache_toolbox_modified.egg-info/requires.txt
django_cache_toolbox_modified.egg-info/top_level.txt