Metadata-Version: 1.0
Name: django-cache-toolbox-modified
Version: 0.1.0
Summary: Non-magical object caching for Django. Based on django-cache-toolbox by Playfire.com
Home-page: http://pypi.python.org/pypi/django-cache-toolbox-modified/
Author: Matt Long
Author-email: matt@mattlong.org
License: BSD
Platform: UNKNOWN
Classifier: Programming Language :: Python
Classifier: Programming Language :: Python :: 2
Classifier: Operating System :: Unix
Classifier: Development Status :: 3 - Alpha
Classifier: Intended Audience :: Developers
Classifier: Intended Audience :: System Administrators
Classifier: Topic :: Software Development :: Libraries :: Python Modules
